{
  "root_envelope_id": "root_000184",
  "root_join_key": "تقن",
  "root_norm": "ت ق ن",
  "v4_roots": [
    {
      "root_id": "root_000184",
      "root_norm": "ت ق ن",
      "source_root_norm": "ت ق ن",
      "registry_status": "pass1_complete",
      "covered_by": "maqayis;ayn;tahdhib",
      "surah_list": "27",
      "pass1_path": "v4/inputs/root_000184.pass1.tsv",
      "pass2_branch_path": "v4/outputs/pass2_branches/root_000184.branches.tsv",
      "pass2_review_path": null,
      "pass3_sense_path": "v4/outputs/pass3_senses/root_000184.senses.tsv",
      "pass3_review_path": null,
      "has_pass1": 1,
      "has_pass2_branches": 1,
      "has_pass2_reviews": 0,
      "has_pass3_senses": 1,
      "has_pass3_reviews": 0
    }
  ],
  "branches": [
    {
      "root_id": "root_000184",
      "branch_id": "B001",
      "branch_image_ar": "إتقان الشيء وحذق العمل",
      "branch_image_en": "making a thing firm and mastering work",
      "image_en_fit": "close",
      "image_en_gap_note": "-",
      "what_is_ar": "إحكام الشيء؛ الحذق بالعمل؛ حضور المنطق والجواب؛ الفصاحة من السوس؛ المثل بابن تقن في جودة الرمي",
      "what_is_en": "Making or doing something with firm mastery; being skilled, articulate, and well-managed; the proverb of Ibn Taqn for excellent archery.",
      "what_is_not_ar": "التَّقْن بمعنى رسابة الماء والطين والحمأة وإصلاح الأرض بها",
      "source_refs": "0395IbnFarisQazwini.MucjamMaqayis.JK008008-ara1:heading:411;ayn:file=0170KhalilFarahidi.Cayn.JK000930-ara1:section=heading%3A3273:headword=%D8%AA%D9%82%D9%86:root=%D8%AA%20%D9%82%20%D9%86:sha=2cd18150628f074b;tahdhib:file=tahdhib.sqlite_original:section=parent_entry_id%3D466%3Bsegment_index%3D87:headword=%D8%AA%D9%82%D9%86:root=%D8%AA%20%D9%82%20%D9%86:sha=a1c47190edcc057a",
      "source_phrase_ar": "أتقنت الشيء أحكمته (maqayis); الإتقان الإحكام (ayn;tahdhib); رجل تَقِن حاذق (maqayis;tahdhib); رجل تَقِن وهو الحاضر المنطق والجواب (tahdhib); الفصاحة من تقنه أي من سوسه (tahdhib); ابن تقن رجل كان جيد الرمي يضرب به المثل (maqayis); أرمى من ابن تقن (maqayis;tahdhib)",
      "status": "accepted",
      "review_note": "Maqayis places أتقنت الشيء, رجل تقن, and ابن تقن under the first أصل, إحكام الشيء; Tahdhib says ابن تقن is the origin of the expression and then extension to every skilled worker.",
      "origin_corpus": "quranic",
      "contaminated": "no"
    },
    {
      "root_id": "root_000184",
      "branch_id": "B002",
      "branch_image_ar": "التَّقْن رسابة الماء والطين",
      "branch_image_en": "sediment-rich water and clay",
      "image_en_fit": "close",
      "image_en_gap_note": "-",
      "what_is_ar": "رسابة الماء الخاثر في الربيع؛ الطين والحمأة؛ إصلاح الأرض بإرسال الماء الخاثر أو الطين فيها",
      "what_is_en": "The springtime sediment or thick water, clay and black mud, and improving land by sending that material into it.",
      "what_is_not_ar": "الإتقان بمعنى الإحكام؛ الحذق بالعمل؛ المثل بابن تقن",
      "source_refs": "0395IbnFarisQazwini.MucjamMaqayis.JK008008-ara1:heading:411;ayn:file=0170KhalilFarahidi.Cayn.JK000930-ara1:section=heading%3A3273:headword=%D8%AA%D9%82%D9%86:root=%D8%AA%20%D9%82%20%D9%86:sha=2cd18150628f074b;tahdhib:file=tahdhib.sqlite_original:section=parent_entry_id%3D466%3Bsegment_index%3D87:headword=%D8%AA%D9%82%D9%86:root=%D8%AA%20%D9%82%20%D9%86:sha=a1c47190edcc057a",
      "source_phrase_ar": "الطين والحمأة (maqayis); التَّقْن رسابة الماء في الربيع (ayn;tahdhib); يجيء به الماء من الخثورة (ayn;tahdhib); تقنوا أرضهم أي أرسلوا فيها الماء الخاثر لتجود (ayn;tahdhib); تقنوا أرضهم إذا أصلحوها بذلك وذلك هو التَّقْن (maqayis)",
      "status": "accepted",
      "review_note": "Maqayis names this as the second أصل, الطين والحمأة; Ayn and Tahdhib describe التقن as spring sediment brought by thick water and the action of improving land with it.",
      "origin_corpus": "quranic",
      "contaminated": "no"
    }
  ],
  "dictionary_sources": [
    {
      "root_id": "root_000184",
      "source_id": "ayn",
      "source_ref": "ayn:file=0170KhalilFarahidi.Cayn.JK000930-ara1:section=heading%3A3273:headword=%D8%AA%D9%82%D9%86:root=%D8%AA%20%D9%82%20%D9%86:sha=2cd18150628f074b",
      "db_root_norm": "ت ق ن",
      "headword": "تقن",
      "lemma": "تقن",
      "section_path": "heading:3273",
      "page_or_volume_ref": "-",
      "entry_text_clean": "# تقن # التقن رسابة الماء في الربيع وهو الذي يجيء به الماء من الخثورة # وتقنوا أرضهم أي أرسلوا فيها الماء الخاثر لتجود # والإتقان ms0628 الإحكام قال # ( ولكنه بالسهل أتقن مولد % ) # أي هو بالسهل أعرف منه بالجبل",
      "route_status": "exact",
      "route_note": "accepted Quran-scoped route: match_method=normalized_exact_root;route_source=scoped_exact_or_reviewed_route;db_root_norm=ت ق ن;db_root_key=ت ق ن;target_root_norm=ت ق ن;target_root_key=ت ق ن",
      "origin_corpus": "quranic"
    },
    {
      "root_id": "root_000184",
      "source_id": "jamhara",
      "source_ref": "-",
      "db_root_norm": "-",
      "headword": "-",
      "lemma": "-",
      "section_path": "-",
      "page_or_volume_ref": "-",
      "entry_text_clean": "-",
      "route_status": "no_match",
      "route_note": "no accepted quran_searchable_entries route, no accepted quran_corpus_search_roots route, and no exact root_norm match",
      "origin_corpus": "quranic"
    },
    {
      "root_id": "root_000184",
      "source_id": "maqayis",
      "source_ref": "0395IbnFarisQazwini.MucjamMaqayis.JK008008-ara1:heading:411",
      "db_root_norm": "ت ق ن",
      "headword": "تقن",
      "lemma": "-",
      "section_path": "-",
      "page_or_volume_ref": "-",
      "entry_text_clean": "# | ( تقن ) التاء والقاف والنون أصلان إحدهما إحكام الشيء والثاني الطين ~~والحمأة | فالقول الأول أتقنت الشيء أحكمته | ورجل تقن | حاذق | وابن تقن ~~رجل كان جيد الرمي يضرب به المثل | قال : # % يرمي بها أرمى من ابن تقن % % PageV01P350 @351@ | وأما الحمأة والطين ~~فيقال تقنوا أرضهم إذا أصلحوها بذلك وذلك هو التقن",
      "route_status": "exact",
      "route_note": "accepted Quran-scoped route: match_method=exact_maqayis;route_source=scoped_maqayis_audit;db_root_norm=ت ق ن;db_root_key=ت ق ن;target_root_norm=ت ق ن;target_root_key=ت ق ن",
      "origin_corpus": "quranic"
    },
    {
      "root_id": "root_000184",
      "source_id": "mufradat",
      "source_ref": "-",
      "db_root_norm": "-",
      "headword": "-",
      "lemma": "-",
      "section_path": "-",
      "page_or_volume_ref": "-",
      "entry_text_clean": "-",
      "route_status": "no_match",
      "route_note": "no accepted quran_searchable_entries route, no accepted quran_corpus_search_roots route, and no exact root_norm match",
      "origin_corpus": "quranic"
    },
    {
      "root_id": "root_000184",
      "source_id": "sihah",
      "source_ref": "-",
      "db_root_norm": "-",
      "headword": "-",
      "lemma": "-",
      "section_path": "-",
      "page_or_volume_ref": "-",
      "entry_text_clean": "-",
      "route_status": "no_match",
      "route_note": "no accepted quran_searchable_entries route, no accepted quran_corpus_search_roots route, and no exact root_norm match",
      "origin_corpus": "quranic"
    },
    {
      "root_id": "root_000184",
      "source_id": "tahdhib",
      "source_ref": "tahdhib:file=tahdhib.sqlite_original:section=parent_entry_id%3D466%3Bsegment_index%3D87:headword=%D8%AA%D9%82%D9%86:root=%D8%AA%20%D9%82%20%D9%86:sha=a1c47190edcc057a",
      "db_root_norm": "ت ق ن",
      "headword": "تقن",
      "lemma": "ت ق ن",
      "section_path": "parent_entry_id=466;segment_index=87",
      "page_or_volume_ref": "-",
      "entry_text_clean": "# تقن : قال الليث : التقن : رسابة الماء في الربيع ، وهو الذي يجيء به ~~الماء من الخثورة ؛ يقال : تقنوا أرضهم ، أي : أرسلوا فيها الماء الخاثر ~~لتجود . قال : والإتقان : الإحكام للأشياء . # أبو عبيد : يقال : رجل تقن ، وهو الحاضر المنطق والجواب . # وقال الفراء : رجل تقن حاذق بالأشياء ، ويقال : الفصاحة من تقنه ، أي : ~~من سوسه . # وقال ابن السكيت : ابن تقن : رجل من عاد ، ولم يكن يسقط له سهم . # وأنشد : # لأكلة من أقط وسمن # ألين مسا في حوايا البطن # من يثربيات قذاذ خشن # يرمي بها أرمى من ابن تقن # قلت : الأصل في التقن ابن تقن هذا ، ثم قيل لكل حاذق في عمل يعمله عالم ~~بأمره تقن ، ومنه يقال : أتقن فلان أمره : إذا أحكمه . # أنشد شمر لسليمان بن ربيعة بن ريان بن عامر بن ثعلبة بن السيد : # أهلكن طسما وبعدهم # غذي بهم وذا جدون # وأهل جاش ومأرب # وحي لقمان والتقون # واليسر كالعسر والغنى كال # عدم والحياة كالمنون # التقون ، من بني تقن بن عاد ، منهم عمرو بن تقن ، وكعب بن تقن ، وبه ضرب ~~المثل فقيل : ( أرمى من ابن تقن ) .",
      "route_status": "exact",
      "route_note": "accepted Quran-scoped route: match_method=normalized_exact_root;route_source=scoped_exact_or_reviewed_route;db_root_norm=ت ق ن;db_root_key=ت ق ن;target_root_norm=ت ق ن;target_root_key=ت ق ن",
      "origin_corpus": "quranic"
    }
  ],
  "lexical_senses": [
    {
      "root_id": "root_000184",
      "lexical_unit_id": "lu_001",
      "expression_ar": "أتقن الشيء",
      "unit_kind": "form",
      "branch_ids": "B001",
      "sense_ar": "أحكم الشيء وأتقنه",
      "sense_en": "firmly mastered or perfected a thing",
      "sense_en_fit": "close",
      "sense_en_gap_note": "-",
      "source_refs": "0395IbnFarisQazwini.MucjamMaqayis.JK008008-ara1:heading:411;ayn:file=0170KhalilFarahidi.Cayn.JK000930-ara1:section=heading%3A3273:headword=%D8%AA%D9%82%D9%86:root=%D8%AA%20%D9%82%20%D9%86:sha=2cd18150628f074b;tahdhib:file=tahdhib.sqlite_original:section=parent_entry_id%3D466%3Bsegment_index%3D87:headword=%D8%AA%D9%82%D9%86:root=%D8%AA%20%D9%82%20%D9%86:sha=a1c47190edcc057a",
      "branch_source_refs": "0395IbnFarisQazwini.MucjamMaqayis.JK008008-ara1:heading:411;ayn:file=0170KhalilFarahidi.Cayn.JK000930-ara1:section=heading%3A3273:headword=%D8%AA%D9%82%D9%86:root=%D8%AA%20%D9%82%20%D9%86:sha=2cd18150628f074b;tahdhib:file=tahdhib.sqlite_original:section=parent_entry_id%3D466%3Bsegment_index%3D87:headword=%D8%AA%D9%82%D9%86:root=%D8%AA%20%D9%82%20%D9%86:sha=a1c47190edcc057a",
      "source_phrase_ar": "أتقنت الشيء أحكمته (maqayis)؛ والإتقان الإحكام (ayn)؛ أتقن فلان أمره إذا أحكمه (tahdhib)",
      "status": "accepted",
      "review_note": "-",
      "corpus_link_status": "not_form_unit",
      "corpus_link_count": 0,
      "resolved_quran_stem_ar": null,
      "resolved_quran_tag": null,
      "origin_corpus": "quranic"
    },
    {
      "root_id": "root_000184",
      "lexical_unit_id": "lu_002",
      "expression_ar": "الإتقان",
      "unit_kind": "form",
      "branch_ids": "B001",
      "sense_ar": "الإحكام للأشياء",
      "sense_en": "mastery or firm perfection of things",
      "sense_en_fit": "close",
      "sense_en_gap_note": "-",
      "source_refs": "ayn:file=0170KhalilFarahidi.Cayn.JK000930-ara1:section=heading%3A3273:headword=%D8%AA%D9%82%D9%86:root=%D8%AA%20%D9%82%20%D9%86:sha=2cd18150628f074b;tahdhib:file=tahdhib.sqlite_original:section=parent_entry_id%3D466%3Bsegment_index%3D87:headword=%D8%AA%D9%82%D9%86:root=%D8%AA%20%D9%82%20%D9%86:sha=a1c47190edcc057a",
      "branch_source_refs": "0395IbnFarisQazwini.MucjamMaqayis.JK008008-ara1:heading:411;ayn:file=0170KhalilFarahidi.Cayn.JK000930-ara1:section=heading%3A3273:headword=%D8%AA%D9%82%D9%86:root=%D8%AA%20%D9%82%20%D9%86:sha=2cd18150628f074b;tahdhib:file=tahdhib.sqlite_original:section=parent_entry_id%3D466%3Bsegment_index%3D87:headword=%D8%AA%D9%82%D9%86:root=%D8%AA%20%D9%82%20%D9%86:sha=a1c47190edcc057a",
      "source_phrase_ar": "الإتقان الإحكام (ayn)؛ والإتقان الإحكام للأشياء (tahdhib)",
      "status": "accepted",
      "review_note": "-",
      "corpus_link_status": "not_form_unit",
      "corpus_link_count": 0,
      "resolved_quran_stem_ar": null,
      "resolved_quran_tag": null,
      "origin_corpus": "quranic"
    },
    {
      "root_id": "root_000184",
      "lexical_unit_id": "lu_003",
      "expression_ar": "تَقِن",
      "unit_kind": "form",
      "branch_ids": "B001",
      "sense_ar": "حاذق بالأشياء عالم بعمله حاضر المنطق والجواب",
      "sense_en": "skilled in things, knowing his work, ready in speech and reply",
      "sense_en_fit": "close",
      "sense_en_gap_note": "-",
      "source_refs": "0395IbnFarisQazwini.MucjamMaqayis.JK008008-ara1:heading:411;tahdhib:file=tahdhib.sqlite_original:section=parent_entry_id%3D466%3Bsegment_index%3D87:headword=%D8%AA%D9%82%D9%86:root=%D8%AA%20%D9%82%20%D9%86:sha=a1c47190edcc057a",
      "branch_source_refs": "0395IbnFarisQazwini.MucjamMaqayis.JK008008-ara1:heading:411;ayn:file=0170KhalilFarahidi.Cayn.JK000930-ara1:section=heading%3A3273:headword=%D8%AA%D9%82%D9%86:root=%D8%AA%20%D9%82%20%D9%86:sha=2cd18150628f074b;tahdhib:file=tahdhib.sqlite_original:section=parent_entry_id%3D466%3Bsegment_index%3D87:headword=%D8%AA%D9%82%D9%86:root=%D8%AA%20%D9%82%20%D9%86:sha=a1c47190edcc057a",
      "source_phrase_ar": "رجل تقن حاذق (maqayis)؛ رجل تقن وهو الحاضر المنطق والجواب (tahdhib)؛ رجل تقن حاذق بالأشياء (tahdhib)؛ لكل حاذق في عمل يعمله عالم بأمره تقن (tahdhib)",
      "status": "accepted",
      "review_note": "-",
      "corpus_link_status": "not_form_unit",
      "corpus_link_count": 0,
      "resolved_quran_stem_ar": null,
      "resolved_quran_tag": null,
      "origin_corpus": "quranic"
    },
    {
      "root_id": "root_000184",
      "lexical_unit_id": "lu_004",
      "expression_ar": "من تقنه",
      "unit_kind": "lexical_unit",
      "branch_ids": "B001",
      "sense_ar": "من سوسه وحسن تدبيره",
      "sense_en": "from his discipline or sound management",
      "sense_en_fit": "close",
      "sense_en_gap_note": "-",
      "source_refs": "tahdhib:file=tahdhib.sqlite_original:section=parent_entry_id%3D466%3Bsegment_index%3D87:headword=%D8%AA%D9%82%D9%86:root=%D8%AA%20%D9%82%20%D9%86:sha=a1c47190edcc057a",
      "branch_source_refs": "0395IbnFarisQazwini.MucjamMaqayis.JK008008-ara1:heading:411;ayn:file=0170KhalilFarahidi.Cayn.JK000930-ara1:section=heading%3A3273:headword=%D8%AA%D9%82%D9%86:root=%D8%AA%20%D9%82%20%D9%86:sha=2cd18150628f074b;tahdhib:file=tahdhib.sqlite_original:section=parent_entry_id%3D466%3Bsegment_index%3D87:headword=%D8%AA%D9%82%D9%86:root=%D8%AA%20%D9%82%20%D9%86:sha=a1c47190edcc057a",
      "source_phrase_ar": "الفصاحة من تقنه أي من سوسه (tahdhib)",
      "status": "accepted",
      "review_note": "Single-source Tahdhib lexical expression under the skill and management branch.",
      "corpus_link_status": "not_form_unit",
      "corpus_link_count": 0,
      "resolved_quran_stem_ar": null,
      "resolved_quran_tag": null,
      "origin_corpus": "quranic"
    },
    {
      "root_id": "root_000184",
      "lexical_unit_id": "lu_005",
      "expression_ar": "أرمى من ابن تقن",
      "unit_kind": "collocation",
      "branch_ids": "B001",
      "sense_ar": "مثل في جودة الرمي وشدة الحذق به",
      "sense_en": "proverb for excellent archery and skill at shooting",
      "sense_en_fit": "close",
      "sense_en_gap_note": "-",
      "source_refs": "0395IbnFarisQazwini.MucjamMaqayis.JK008008-ara1:heading:411;tahdhib:file=tahdhib.sqlite_original:section=parent_entry_id%3D466%3Bsegment_index%3D87:headword=%D8%AA%D9%82%D9%86:root=%D8%AA%20%D9%82%20%D9%86:sha=a1c47190edcc057a",
      "branch_source_refs": "0395IbnFarisQazwini.MucjamMaqayis.JK008008-ara1:heading:411;ayn:file=0170KhalilFarahidi.Cayn.JK000930-ara1:section=heading%3A3273:headword=%D8%AA%D9%82%D9%86:root=%D8%AA%20%D9%82%20%D9%86:sha=2cd18150628f074b;tahdhib:file=tahdhib.sqlite_original:section=parent_entry_id%3D466%3Bsegment_index%3D87:headword=%D8%AA%D9%82%D9%86:root=%D8%AA%20%D9%82%20%D9%86:sha=a1c47190edcc057a",
      "source_phrase_ar": "ابن تقن رجل كان جيد الرمي يضرب به المثل (maqayis)؛ أرمى من ابن تقن (maqayis;tahdhib)؛ ابن تقن رجل من عاد ولم يكن يسقط له سهم (tahdhib)",
      "status": "accepted",
      "review_note": "Proverb collocation, not promoted into the bare adjective beyond the separately attested تَقِن row.",
      "corpus_link_status": "not_form_unit",
      "corpus_link_count": 0,
      "resolved_quran_stem_ar": null,
      "resolved_quran_tag": null,
      "origin_corpus": "quranic"
    },
    {
      "root_id": "root_000184",
      "lexical_unit_id": "lu_006",
      "expression_ar": "التَّقْن",
      "unit_kind": "form",
      "branch_ids": "B002",
      "sense_ar": "رسابة الماء الخاثر في الربيع والطين والحمأة",
      "sense_en": "spring sediment of thick water, clay, and black mud",
      "sense_en_fit": "close",
      "sense_en_gap_note": "-",
      "source_refs": "0395IbnFarisQazwini.MucjamMaqayis.JK008008-ara1:heading:411;ayn:file=0170KhalilFarahidi.Cayn.JK000930-ara1:section=heading%3A3273:headword=%D8%AA%D9%82%D9%86:root=%D8%AA%20%D9%82%20%D9%86:sha=2cd18150628f074b;tahdhib:file=tahdhib.sqlite_original:section=parent_entry_id%3D466%3Bsegment_index%3D87:headword=%D8%AA%D9%82%D9%86:root=%D8%AA%20%D9%82%20%D9%86:sha=a1c47190edcc057a",
      "branch_source_refs": "0395IbnFarisQazwini.MucjamMaqayis.JK008008-ara1:heading:411;ayn:file=0170KhalilFarahidi.Cayn.JK000930-ara1:section=heading%3A3273:headword=%D8%AA%D9%82%D9%86:root=%D8%AA%20%D9%82%20%D9%86:sha=2cd18150628f074b;tahdhib:file=tahdhib.sqlite_original:section=parent_entry_id%3D466%3Bsegment_index%3D87:headword=%D8%AA%D9%82%D9%86:root=%D8%AA%20%D9%82%20%D9%86:sha=a1c47190edcc057a",
      "source_phrase_ar": "الطين والحمأة (maqayis)؛ التقن رسابة الماء في الربيع (ayn;tahdhib)؛ يجيء به الماء من الخثورة (ayn;tahdhib)",
      "status": "accepted",
      "review_note": "-",
      "corpus_link_status": "not_form_unit",
      "corpus_link_count": 0,
      "resolved_quran_stem_ar": null,
      "resolved_quran_tag": null,
      "origin_corpus": "quranic"
    },
    {
      "root_id": "root_000184",
      "lexical_unit_id": "lu_007",
      "expression_ar": "تقنوا أرضهم",
      "unit_kind": "collocation",
      "branch_ids": "B002",
      "sense_ar": "أرسلوا فيها الماء الخاثر أو الطين لتجود أو تصلح",
      "sense_en": "sent thick sediment-rich water or clay into their land so it would improve",
      "sense_en_fit": "close",
      "sense_en_gap_note": "-",
      "source_refs": "0395IbnFarisQazwini.MucjamMaqayis.JK008008-ara1:heading:411;ayn:file=0170KhalilFarahidi.Cayn.JK000930-ara1:section=heading%3A3273:headword=%D8%AA%D9%82%D9%86:root=%D8%AA%20%D9%82%20%D9%86:sha=2cd18150628f074b;tahdhib:file=tahdhib.sqlite_original:section=parent_entry_id%3D466%3Bsegment_index%3D87:headword=%D8%AA%D9%82%D9%86:root=%D8%AA%20%D9%82%20%D9%86:sha=a1c47190edcc057a",
      "branch_source_refs": "0395IbnFarisQazwini.MucjamMaqayis.JK008008-ara1:heading:411;ayn:file=0170KhalilFarahidi.Cayn.JK000930-ara1:section=heading%3A3273:headword=%D8%AA%D9%82%D9%86:root=%D8%AA%20%D9%82%20%D9%86:sha=2cd18150628f074b;tahdhib:file=tahdhib.sqlite_original:section=parent_entry_id%3D466%3Bsegment_index%3D87:headword=%D8%AA%D9%82%D9%86:root=%D8%AA%20%D9%82%20%D9%86:sha=a1c47190edcc057a",
      "source_phrase_ar": "تقنوا أرضهم إذا أصلحوها بذلك وذلك هو التقن (maqayis)؛ تقنوا أرضهم أي أرسلوا فيها الماء الخاثر لتجود (ayn;tahdhib)",
      "status": "accepted",
      "review_note": "-",
      "corpus_link_status": "not_form_unit",
      "corpus_link_count": 0,
      "resolved_quran_stem_ar": null,
      "resolved_quran_tag": null,
      "origin_corpus": "quranic"
    },
    {
      "root_id": "root_000184",
      "lexical_unit_id": "lu_008",
      "expression_ar": "التقون",
      "unit_kind": "lexical_unit",
      "branch_ids": "B001",
      "sense_ar": "قوم من بني تقن بن عاد",
      "sense_en": "people from the lineage of Taqn son of Aad",
      "sense_en_fit": "close",
      "sense_en_gap_note": "-",
      "source_refs": "tahdhib:file=tahdhib.sqlite_original:section=parent_entry_id%3D466%3Bsegment_index%3D87:headword=%D8%AA%D9%82%D9%86:root=%D8%AA%20%D9%82%20%D9%86:sha=a1c47190edcc057a",
      "branch_source_refs": "0395IbnFarisQazwini.MucjamMaqayis.JK008008-ara1:heading:411;ayn:file=0170KhalilFarahidi.Cayn.JK000930-ara1:section=heading%3A3273:headword=%D8%AA%D9%82%D9%86:root=%D8%AA%20%D9%82%20%D9%86:sha=2cd18150628f074b;tahdhib:file=tahdhib.sqlite_original:section=parent_entry_id%3D466%3Bsegment_index%3D87:headword=%D8%AA%D9%82%D9%86:root=%D8%AA%20%D9%82%20%D9%86:sha=a1c47190edcc057a",
      "source_phrase_ar": "وحي لقمان والتقون (tahdhib)؛ التقون من بني تقن بن عاد منهم عمرو بن تقن وكعب بن تقن (tahdhib)",
      "status": "accepted",
      "review_note": "Proper-name lexical unit retained from Tahdhib; linked to B001 because Tahdhib treats ابن تقن as the origin for the later skill expression.",
      "corpus_link_status": "not_form_unit",
      "corpus_link_count": 0,
      "resolved_quran_stem_ar": null,
      "resolved_quran_tag": null,
      "origin_corpus": "quranic"
    }
  ],
  "branch_lexical_links": [
    {
      "root_id": "root_000184",
      "branch_id": "B001",
      "lexical_unit_id": "lu_001",
      "link_source": "pass3_branch_ids"
    },
    {
      "root_id": "root_000184",
      "branch_id": "B001",
      "lexical_unit_id": "lu_002",
      "link_source": "pass3_branch_ids"
    },
    {
      "root_id": "root_000184",
      "branch_id": "B001",
      "lexical_unit_id": "lu_003",
      "link_source": "pass3_branch_ids"
    },
    {
      "root_id": "root_000184",
      "branch_id": "B001",
      "lexical_unit_id": "lu_004",
      "link_source": "pass3_branch_ids"
    },
    {
      "root_id": "root_000184",
      "branch_id": "B001",
      "lexical_unit_id": "lu_005",
      "link_source": "pass3_branch_ids"
    },
    {
      "root_id": "root_000184",
      "branch_id": "B001",
      "lexical_unit_id": "lu_008",
      "link_source": "pass3_branch_ids"
    },
    {
      "root_id": "root_000184",
      "branch_id": "B002",
      "lexical_unit_id": "lu_006",
      "link_source": "pass3_branch_ids"
    },
    {
      "root_id": "root_000184",
      "branch_id": "B002",
      "lexical_unit_id": "lu_007",
      "link_source": "pass3_branch_ids"
    }
  ],
  "qac": {
    "summary": {
      "morpheme_count": 1,
      "word_count": 1,
      "ayah_count": 1,
      "surah_count": 1,
      "lemmas": {
        "أَتْقَنَ": 1
      },
      "parts_of_speech": {
        "V": 1
      },
      "measures": {
        "IV": 1
      }
    },
    "occurrences": [
      {
        "qac_ref": "27:88:12:1",
        "qac_word_ref": "27:88:12",
        "surah": 27,
        "ayah": 88,
        "word_index": 12,
        "morpheme_index": 1,
        "surface_bw": ">atoqana",
        "surface_ar": "أَتْقَنَ",
        "stem_ar": "أَتْقَنَ",
        "lemma_bw": ">atoqana",
        "lemma_ar": "أَتْقَنَ",
        "root_raw": "tqn",
        "root_ar": "ت ق ن",
        "source_pos": "V",
        "pos": "V",
        "morpheme_role": "STEM",
        "measure": "IV",
        "aspect": "PERF",
        "mood": "",
        "voice": "",
        "morph_features": "STEM|POS:V|PERF|(IV)|LEM:>atoqana|ROOT:tqn|3MS"
      }
    ],
    "ayah_contexts": [
      {
        "ref": "27:88",
        "surah": 27,
        "ayah": 88,
        "surface_ar": "وَتَرَى ٱلْجِبَالَ تَحْسَبُهَا جَامِدَةً وَهِىَ تَمُرُّ مَرَّ ٱلسَّحَابِ صُنْعَ ٱللَّهِ ٱلَّذِىٓ أَتْقَنَ كُلَّ شَىْءٍ إِنَّهُۥ خَبِيرٌۢ بِمَا تَفْعَلُونَ",
        "words": [
          {
            "qac_word_ref": "27:88:1",
            "surah": 27,
            "ayah": 88,
            "word_index": 1,
            "surface_bw": "wataraY",
            "surface_ar": "وَتَرَى",
            "root_join_keys": "رءي",
            "lemmas_ar": "رَءَا",
            "pos_tags": "CONJ;V",
            "measures": ""
          },
          {
            "qac_word_ref": "27:88:2",
            "surah": 27,
            "ayah": 88,
            "word_index": 2,
            "surface_bw": "{lojibaAla",
            "surface_ar": "ٱلْجِبَالَ",
            "root_join_keys": "جبل",
            "lemmas_ar": "جَبَل",
            "pos_tags": "DET;N",
            "measures": ""
          },
          {
            "qac_word_ref": "27:88:3",
            "surah": 27,
            "ayah": 88,
            "word_index": 3,
            "surface_bw": "taHosabuhaA",
            "surface_ar": "تَحْسَبُهَا",
            "root_join_keys": "حسب",
            "lemmas_ar": "حَسِبَ",
            "pos_tags": "V;PRON",
            "measures": ""
          },
          {
            "qac_word_ref": "27:88:4",
            "surah": 27,
            "ayah": 88,
            "word_index": 4,
            "surface_bw": "jaAmidapF",
            "surface_ar": "جَامِدَةً",
            "root_join_keys": "جمد",
            "lemmas_ar": "جَامِدَة",
            "pos_tags": "N",
            "measures": ""
          },
          {
            "qac_word_ref": "27:88:5",
            "surah": 27,
            "ayah": 88,
            "word_index": 5,
            "surface_bw": "wahiYa",
            "surface_ar": "وَهِىَ",
            "root_join_keys": "",
            "lemmas_ar": "",
            "pos_tags": "CIRC;PRON",
            "measures": ""
          },
          {
            "qac_word_ref": "27:88:6",
            "surah": 27,
            "ayah": 88,
            "word_index": 6,
            "surface_bw": "tamur~u",
            "surface_ar": "تَمُرُّ",
            "root_join_keys": "مرر",
            "lemmas_ar": "مَرَّ",
            "pos_tags": "V",
            "measures": ""
          },
          {
            "qac_word_ref": "27:88:7",
            "surah": 27,
            "ayah": 88,
            "word_index": 7,
            "surface_bw": "mar~a",
            "surface_ar": "مَرَّ",
            "root_join_keys": "مرر",
            "lemmas_ar": "مَرّ",
            "pos_tags": "N",
            "measures": ""
          },
          {
            "qac_word_ref": "27:88:8",
            "surah": 27,
            "ayah": 88,
            "word_index": 8,
            "surface_bw": "{ls~aHaAbi",
            "surface_ar": "ٱلسَّحَابِ",
            "root_join_keys": "سحب",
            "lemmas_ar": "سَحَاب",
            "pos_tags": "DET;N",
            "measures": ""
          },
          {
            "qac_word_ref": "27:88:9",
            "surah": 27,
            "ayah": 88,
            "word_index": 9,
            "surface_bw": "SunoEa",
            "surface_ar": "صُنْعَ",
            "root_join_keys": "صنع",
            "lemmas_ar": "صُنْع",
            "pos_tags": "N",
            "measures": ""
          },
          {
            "qac_word_ref": "27:88:10",
            "surah": 27,
            "ayah": 88,
            "word_index": 10,
            "surface_bw": "{ll~ahi",
            "surface_ar": "ٱللَّهِ",
            "root_join_keys": "ءله",
            "lemmas_ar": "ٱللَّه",
            "pos_tags": "PN",
            "measures": ""
          },
          {
            "qac_word_ref": "27:88:11",
            "surah": 27,
            "ayah": 88,
            "word_index": 11,
            "surface_bw": "{l~a*iY^",
            "surface_ar": "ٱلَّذِىٓ",
            "root_join_keys": "",
            "lemmas_ar": "ٱلَّذِى",
            "pos_tags": "REL",
            "measures": ""
          },
          {
            "qac_word_ref": "27:88:12",
            "surah": 27,
            "ayah": 88,
            "word_index": 12,
            "surface_bw": ">atoqana",
            "surface_ar": "أَتْقَنَ",
            "root_join_keys": "تقن",
            "lemmas_ar": "أَتْقَنَ",
            "pos_tags": "V",
            "measures": "IV"
          },
          {
            "qac_word_ref": "27:88:13",
            "surah": 27,
            "ayah": 88,
            "word_index": 13,
            "surface_bw": "kul~a",
            "surface_ar": "كُلَّ",
            "root_join_keys": "كلل",
            "lemmas_ar": "كُلّ",
            "pos_tags": "N",
            "measures": ""
          },
          {
            "qac_word_ref": "27:88:14",
            "surah": 27,
            "ayah": 88,
            "word_index": 14,
            "surface_bw": "$aYo'K",
            "surface_ar": "شَىْءٍ",
            "root_join_keys": "شيء",
            "lemmas_ar": "شَىْء",
            "pos_tags": "N",
            "measures": ""
          },
          {
            "qac_word_ref": "27:88:15",
            "surah": 27,
            "ayah": 88,
            "word_index": 15,
            "surface_bw": "<in~ahu,",
            "surface_ar": "إِنَّهُۥ",
            "root_join_keys": "",
            "lemmas_ar": "إِنّ",
            "pos_tags": "ACC;PRON",
            "measures": ""
          },
          {
            "qac_word_ref": "27:88:16",
            "surah": 27,
            "ayah": 88,
            "word_index": 16,
            "surface_bw": "xabiyrN[",
            "surface_ar": "خَبِيرٌۢ",
            "root_join_keys": "خبر",
            "lemmas_ar": "خَبِير",
            "pos_tags": "N",
            "measures": ""
          },
          {
            "qac_word_ref": "27:88:17",
            "surah": 27,
            "ayah": 88,
            "word_index": 17,
            "surface_bw": "bimaA",
            "surface_ar": "بِمَا",
            "root_join_keys": "",
            "lemmas_ar": "مَا",
            "pos_tags": "P;REL",
            "measures": ""
          },
          {
            "qac_word_ref": "27:88:18",
            "surah": 27,
            "ayah": 88,
            "word_index": 18,
            "surface_bw": "tafoEaluwna",
            "surface_ar": "تَفْعَلُونَ",
            "root_join_keys": "فعل",
            "lemmas_ar": "فَعَلَ",
            "pos_tags": "V;PRON",
            "measures": ""
          }
        ]
      }
    ]
  },
  "attachments": {
    "verb_instances": [
      {
        "unit_id": "ae:v3:s027:088:pass1:frame:v5",
        "source_pass": "pass1",
        "source_rtype": "FRAME",
        "source_local_id": "v5",
        "sura": "27",
        "ayah": "88",
        "wid": "14",
        "word_unit_id": "q:27:88:14",
        "surface": "أَتْقَنَ",
        "stem": "أتقن",
        "root_norm": "ت ق ن",
        "form_tag": "PV",
        "grammar": "PV perfect 3ms, Form IV afʿala — transitive: made something firm/precise",
        "frame_obj_status": "explicit",
        "object_attachment_ids": "ae:v3:s027:088:pass1:attach:a11",
        "object_wids": "15",
        "object_roots": "ك ل ل",
        "prep_attachment_ids": "",
        "preps": "",
        "prep_object_wids": "",
        "prep_object_roots": "",
        "clausal_attachment_ids": "",
        "subject_attachment_id": "ae:v3:s027:088:pass1:attach:a10",
        "subject_wid": "13",
        "prodrop": "",
        "has_cognate_acc": "0",
        "frame_signature": "obj=explicit|prep=-|clause=no|cognate=no",
        "notes": ""
      }
    ],
    "noun_instances": [],
    "attachments": [
      {
        "unit_id": "ae:v3:s027:088:pass1:attach:a10",
        "source_pass": "pass1",
        "source_rtype": "ATTACH",
        "source_local_id": "a10",
        "sura": "27",
        "ayah": "88",
        "relation": "subject",
        "status": "syntactically_forced",
        "confidence": "high",
        "evidence": "agreement;local_syntax",
        "reason": "الَّذِي is the subject of أَتْقَنَ in the relative clause.",
        "dep_wid": "13",
        "dep_unit_id": "q:27:88:13",
        "dep_surface": "الَّذِي",
        "dep_root_norm": "ل ل ذ",
        "dep_form_tag": "REL_PRON",
        "dep_part": "",
        "head_wid": "14",
        "head_unit_id": "q:27:88:14",
        "head_surface": "أَتْقَنَ",
        "head_root_norm": "ت ق ن",
        "head_form_tag": "PV",
        "head_part": "",
        "obj_type": "",
        "prep_base": "",
        "prep_wid": "",
        "prep_unit_id": "",
        "dep_start_wid": "",
        "dep_end_wid": "",
        "context": "",
        "dep_clause_raw": "",
        "dep_clause_unit_ids": "",
        "head_clause_raw": "",
        "head_clause_unit_ids": "",
        "choice_set_raw": "",
        "choice_relation": ""
      },
      {
        "unit_id": "ae:v3:s027:088:pass1:attach:a11",
        "source_pass": "pass1",
        "source_rtype": "ATTACH",
        "source_local_id": "a11",
        "sura": "27",
        "ayah": "88",
        "relation": "direct_object",
        "status": "syntactically_forced",
        "confidence": "high",
        "evidence": "case_government;word_order",
        "reason": "كُلَّ is the direct object of أَتْقَنَ.",
        "dep_wid": "15",
        "dep_unit_id": "q:27:88:15",
        "dep_surface": "كُلَّ",
        "dep_root_norm": "ك ل ل",
        "dep_form_tag": "NOUN_ABSTRACT",
        "dep_part": "",
        "head_wid": "14",
        "head_unit_id": "q:27:88:14",
        "head_surface": "أَتْقَنَ",
        "head_root_norm": "ت ق ن",
        "head_form_tag": "PV",
        "head_part": "",
        "obj_type": "explicit",
        "prep_base": "",
        "prep_wid": "",
        "prep_unit_id": "",
        "dep_start_wid": "",
        "dep_end_wid": "",
        "context": "",
        "dep_clause_raw": "",
        "dep_clause_unit_ids": "",
        "head_clause_raw": "",
        "head_clause_unit_ids": "",
        "choice_set_raw": "",
        "choice_relation": ""
      }
    ],
    "verb_valency_frames": [
      {
        "root_norm": "ت ق ن",
        "stem": "أتقن",
        "form_tag": "PV",
        "frame_signature": "obj=explicit|prep=-|clause=no|cognate=no",
        "instance_count": "1",
        "sample_refs": "27:88:14",
        "object_status_profile": "explicit:1",
        "prep_profile": "",
        "object_root_profile": "ك ل ل:1",
        "prep_object_root_profile": "",
        "surah_count": "1"
      }
    ],
    "noun_governing_patterns": []
  },
  "qnet": {
    "root_000184/B001": {
      "keywords": [
        {
          "keyword_type": "core",
          "keyword": "mastery",
          "replicate_votes": 2
        },
        {
          "keyword_type": "core",
          "keyword": "precision",
          "replicate_votes": 2
        },
        {
          "keyword_type": "core",
          "keyword": "skill",
          "replicate_votes": 2
        },
        {
          "keyword_type": "core",
          "keyword": "workmanship",
          "replicate_votes": 2
        },
        {
          "keyword_type": "core",
          "keyword": "craft",
          "replicate_votes": 1
        },
        {
          "keyword_type": "core",
          "keyword": "eloquence",
          "replicate_votes": 1
        },
        {
          "keyword_type": "core",
          "keyword": "excellence",
          "replicate_votes": 1
        },
        {
          "keyword_type": "core",
          "keyword": "marksmanship",
          "replicate_votes": 1
        },
        {
          "keyword_type": "core",
          "keyword": "proficiency",
          "replicate_votes": 1
        },
        {
          "keyword_type": "bridge",
          "keyword": "judgment",
          "replicate_votes": 2
        },
        {
          "keyword_type": "bridge",
          "keyword": "performance",
          "replicate_votes": 2
        },
        {
          "keyword_type": "bridge",
          "keyword": "rhetoric",
          "replicate_votes": 2
        },
        {
          "keyword_type": "bridge",
          "keyword": "communication",
          "replicate_votes": 1
        },
        {
          "keyword_type": "bridge",
          "keyword": "competence",
          "replicate_votes": 1
        },
        {
          "keyword_type": "bridge",
          "keyword": "craft",
          "replicate_votes": 1
        },
        {
          "keyword_type": "bridge",
          "keyword": "craftsmanship",
          "replicate_votes": 1
        },
        {
          "keyword_type": "bridge",
          "keyword": "expertise",
          "replicate_votes": 1
        },
        {
          "keyword_type": "bridge",
          "keyword": "quality",
          "replicate_votes": 1
        },
        {
          "keyword_type": "bridge",
          "keyword": "technique",
          "replicate_votes": 1
        }
      ],
      "neighbors": [
        {
          "root_id": "root_000011",
          "branch_id": "B011",
          "root_norm": "ء ث ر",
          "branch_image_ar": "حذق الشيء بالممارسة",
          "what_is_ar": "يدخل فيه قولهم أثر فلان يقول كذا إذا أبصر الشيء وضري بمعرفته وحذقه.",
          "what_is_not_ar": "ليس هو رواية الخبر ولا أثر العلامة الباقية.",
          "source_refs": "tahdhib:file=tahdhib.sqlite_original:section=parent_entry_id%3D775%3Bsegment_index%3D11:headword=%D8%A3%D8%AB%D8%B1:root=%D8%A3%20%D8%AB%20%D8%B1:sha=f0da23eb3e95988a",
          "status": "accepted",
          "contaminated": "no",
          "shared_consensus_core": [
            "mastery",
            "skill"
          ]
        },
        {
          "root_id": "root_000201",
          "branch_id": "B002",
          "root_norm": "ث ق ف",
          "branch_image_ar": "حذق سريع في الإدراك والفعل",
          "what_is_ar": "يدخل فيه الحذق والثقافة وسرعة التعلم والتفهم وضبط ما يسمع أو يحويه، ومنه المثاقفة إذا أخذت من مهارة الفعل.",
          "what_is_not_ar": "ليس اسم القبيلة، ولا حموضة الخل، ولا التقويم الحسي إلا إذا جعل مثالا لتأديب المهارة.",
          "source_refs": "0395IbnFarisQazwini.MucjamMaqayis.JK008008-ara1:heading:478;ayn:file=0170KhalilFarahidi.Cayn.JK000930-ara1:section=heading%3A3295:headword=%D8%AB%D9%82%D9%81:root=%D8%AB%20%D9%82%20%D9%81:sha=8d1edf36410699f0;jamhara:file=0321IbnDuraydAzdi.JamharatLugha.JK007100-ara1:section=heading%3A1141%3Asubentry%3A0%3A%D8%AB%D9%82%D9%81:headword=%D8%AB%D9%82%D9%81:root=%D8%AB%20%D9%82%20%D9%81:sha=d93a6adc5c8143ad;sihah:file=0393IbnHammadJawhari.SihahTajLugha.Shamela0023235-ara1:section=heading%3A3250:headword=%D8%AB%D9%82%D9%81:root=%D8%AB%20%D9%82%20%D9%81:sha=35bf9d18d2ed4231;tahdhib:file=tahdhib.sqlite_original:section=parent_entry_id%3D466%3Bsegment_index%3D120:headword=%D8%AB%D9%82%D9%81:root=%D8%AB%20%D9%82%20%D9%81:sha=54d350d9ae9b8ebb;mufradat:file=0502RaghibIsbahani.Mufradat.Shamela0023636-ara1:section=heading%3A205:headword=%D8%AB%D9%82%D9%81:root=%D8%AB%20%D9%82%20%D9%81:sha=36292d38d414688e",
          "status": "accepted",
          "contaminated": "no",
          "shared_consensus_core": [
            "mastery",
            "skill"
          ]
        },
        {
          "root_id": "root_000348",
          "branch_id": "B004",
          "root_norm": "ح ك م",
          "branch_image_ar": "الإحكام والإتقان والوثاقة",
          "what_is_ar": "إحكام الشيء حتى يستحكم؛ كون الأمر وثيقا أو محكما؛ الآيات المحكمات؛ بلوغ الشيء نهايته في المدح أو السلامة",
          "what_is_not_ar": "القضاء بين الناس؛ الحكمة بمعنى العلم فقط؛ منع السفيه أو الدابة",
          "source_refs": "ayn:file=0170KhalilFarahidi.Cayn.JK000930-ara1:section=heading%3A1425:headword=%D8%AD%D9%83%D9%85:root=%D8%AD%20%D9%83%20%D9%85:sha=1260bcf0bfc41f35;sihah:file=0393IbnHammadJawhari.SihahTajLugha.Shamela0023235-ara1:section=heading%3A4424:headword=%D8%AD%D9%83%D9%85:root=%D8%AD%20%D9%83%20%D9%85:sha=6a057d42407682b4;tahdhib:file=tahdhib.sqlite_original:section=parent_entry_id%3D236%3Bsegment_index%3D8:headword=%D8%AD%D9%83%D9%85:root=%D8%AD%20%D9%83%20%D9%85:sha=68d03247e1b0e2c5;mufradat:file=0502RaghibIsbahani.Mufradat.Shamela0023636-ara1:section=heading%3A350:headword=%D8%AD%D9%83%D9%85:root=%D8%AD%20%D9%83%20%D9%85:sha=6b284f6b3fec6dff",
          "status": "accepted",
          "contaminated": "no",
          "shared_consensus_core": [
            "mastery",
            "precision"
          ]
        },
        {
          "root_id": "root_001024",
          "branch_id": "B007",
          "root_norm": "ع ض ض",
          "branch_image_ar": "قوة مجربة في مال أو سفر أو قتال",
          "what_is_ar": "يدخل فيه عض سفر، وعض مال، وعض قتال: أي القوي المجرب أو الحسن القيام بذلك الباب.",
          "what_is_not_ar": "لا يدخل فيه الدهاء الخلقي ولا الشدة الواقعة على الإنسان ولا العض بالأسنان.",
          "source_refs": "0395IbnFarisQazwini.MucjamMaqayis.JK008008-ara1:heading:2297;sihah:file=0393IbnHammadJawhari.SihahTajLugha.Shamela0023235-ara1:section=heading%3A2675:headword=%D8%B9%D8%B6%D8%B6:root=%D8%B9%20%D8%B6%20%D8%B6:sha=a35d16a5d10c442f;tahdhib:file=tahdhib.sqlite_original:section=parent_entry_id%3D8%3Bsegment_index%3D4:headword=%D8%B9%D8%B6:root=%D8%B9%20%D8%B6:sha=f5ac3f48197ee654",
          "status": "accepted",
          "contaminated": "no",
          "shared_consensus_core": [
            "mastery",
            "skill"
          ]
        },
        {
          "root_id": "root_001149",
          "branch_id": "B001",
          "root_norm": "ف ر ه",
          "branch_image_ar": "حذق الفَاره",
          "what_is_ar": "يدخل فيه الفاره بمعنى الحاذق بالشيء والفراهة التي تدل على الحذق في العمل أو النحت",
          "what_is_not_ar": "لا يدخل فيه الأشر والبطر ولا الحسن والملاحة ولا إنتاج الأولاد الفرهة",
          "source_refs": "ayn:file=0170KhalilFarahidi.Cayn.JK000930-ara1:section=heading%3A2168:headword=%D9%81%D8%B1%D9%87:root=%D9%81%20%D8%B1%20%D9%87:sha=5a52d5f1282cb0ed;sihah:file=0393IbnHammadJawhari.SihahTajLugha.Shamela0023235-ara1:section=heading%3A5158:headword=%D9%81%D8%B1%D9%87:root=%D9%81%20%D8%B1%20%D9%87:sha=a00be076ec5b1a34;tahdhib:file=tahdhib.sqlite_original:section=parent_entry_id%3D295%3Bsegment_index%3D234:headword=%D9%81%D8%B1%D9%87:root=%D9%81%20%D8%B1%20%D9%87:sha=86f02f538ce3bd64;mufradat:file=0502RaghibIsbahani.Mufradat.Shamela0023636-ara1:section=heading%3A1141:headword=%D9%81%D8%B1%D9%87:root=%D9%81%20%D8%B1%20%D9%87:sha=9336d558f07f11db;0395IbnFarisQazwini.MucjamMaqayis.JK008008-ara1:heading:2749",
          "status": "accepted",
          "contaminated": "no",
          "shared_consensus_core": [
            "mastery",
            "skill"
          ]
        },
        {
          "root_id": "root_001479",
          "branch_id": "B008",
          "root_norm": "ن ح ر",
          "branch_image_ar": "نحر العلم إتقانا",
          "what_is_ar": "النحرير، وهو العالم المجرب أو المتقن أو الطبن الفطن الحاذق",
          "what_is_not_ar": "ليس الذبح الحسي؛ وليس الجود بنحر الإبل",
          "source_refs": "0395IbnFarisQazwini.MucjamMaqayis.JK008008-ara1:heading:3550;maqayis:root=%D9%86%20%D8%AD%20%D8%B1:headword=%D9%86%D8%AD%D8%B1:sha=0df9942608304198;sihah:file=0393IbnHammadJawhari.SihahTajLugha.Shamela0023235-ara1:section=heading%3A1933:headword=%D9%86%D8%AD%D8%B1:root=%D9%86%20%D8%AD%20%D8%B1:sha=78a9e1a52d821fb2;tahdhib:file=tahdhib.sqlite_original:section=parent_entry_id%3D237%3Bsegment_index%3D90:headword=%D9%86%D8%AD%D8%B1:root=%D9%86%20%D8%AD%20%D8%B1:sha=c07e5db42685f8a2;mufradat:file=0502RaghibIsbahani.Mufradat.Shamela0023636-ara1:section=heading%3A1472:headword=%D9%86%D8%AD%D8%B1:root=%D9%86%20%D8%AD%20%D8%B1:sha=4e8ec4972fb8dd36",
          "status": "accepted",
          "contaminated": "no",
          "shared_consensus_core": [
            "mastery",
            "skill"
          ]
        }
      ]
    },
    "root_000184/B002": {
      "keywords": [
        {
          "keyword_type": "core",
          "keyword": "clay",
          "replicate_votes": 2
        },
        {
          "keyword_type": "core",
          "keyword": "mud",
          "replicate_votes": 2
        },
        {
          "keyword_type": "core",
          "keyword": "sediment",
          "replicate_votes": 2
        },
        {
          "keyword_type": "core",
          "keyword": "silt",
          "replicate_votes": 2
        },
        {
          "keyword_type": "core",
          "keyword": "sludge",
          "replicate_votes": 2
        },
        {
          "keyword_type": "core",
          "keyword": "water",
          "replicate_votes": 2
        },
        {
          "keyword_type": "core",
          "keyword": "deposit",
          "replicate_votes": 1
        },
        {
          "keyword_type": "bridge",
          "keyword": "agriculture",
          "replicate_votes": 2
        },
        {
          "keyword_type": "bridge",
          "keyword": "hydrology",
          "replicate_votes": 2
        },
        {
          "keyword_type": "bridge",
          "keyword": "sedimentation",
          "replicate_votes": 2
        },
        {
          "keyword_type": "bridge",
          "keyword": "soil",
          "replicate_votes": 2
        },
        {
          "keyword_type": "bridge",
          "keyword": "fertility",
          "replicate_votes": 1
        },
        {
          "keyword_type": "bridge",
          "keyword": "geomorphology",
          "replicate_votes": 1
        },
        {
          "keyword_type": "bridge",
          "keyword": "irrigation",
          "replicate_votes": 1
        },
        {
          "keyword_type": "bridge",
          "keyword": "reclamation",
          "replicate_votes": 1
        },
        {
          "keyword_type": "bridge",
          "keyword": "terrain",
          "replicate_votes": 1
        }
      ],
      "neighbors": [
        {
          "root_id": "root_000354",
          "branch_id": "B001",
          "root_norm": "ح م ء",
          "branch_image_ar": "الحمأة السوداء في الماء",
          "what_is_ar": "الحمأ والحمأة والطين الأسود المنتن، والعين أو البئر إذا صارت ذات حمأة، وإخراج الحمأة منها أو إلقاؤها فيها",
          "what_is_not_ar": "ليس الحرارة ولا الحماية ولا الحمى",
          "source_refs": "ayn:file=0170KhalilFarahidi.Cayn.JK000930-ara1:section=heading%3A1863:headword=%D8%AD%D9%85%D9%89:root=%D8%AD%20%D9%85%20%D9%8A:sha=9283a75f6d7f3a06;sihah:file=0393IbnHammadJawhari.SihahTajLugha.Shamela0023235-ara1:section=heading%3A41:headword=%D8%AD%D9%85%D8%A3:root=%D8%AD%20%D9%85%20%D8%A1:sha=a32c41709791b06c;tahdhib:file=tahdhib.sqlite_original:section=parent_entry_id%3D257%3Bsegment_index%3D3:headword=%D8%AD%D9%85%D8%A3:root=%D8%AD%20%D9%85%20%D8%A3:sha=2520c5f8d1492c9d;mufradat:file=0502RaghibIsbahani.Mufradat.Shamela0023636-ara1:section=heading%3A363:headword=%D8%AD%D9%85%D9%89:root=%D8%AD%20%D9%85%20%D9%8A:sha=2df5f9e72e438838",
          "status": "accepted",
          "contaminated": "no",
          "shared_consensus_core": [
            "mud",
            "sediment",
            "water"
          ]
        },
        {
          "root_id": "root_000358",
          "branch_id": "B006",
          "root_norm": "ح م ي",
          "branch_image_ar": "الحمأة والطين الأسود",
          "what_is_ar": "الحمأ والحمأة والطين الأسود المنتن وما في البئر والعين الحمئة",
          "what_is_not_ar": "ليس حمى الموضع المحظور ولا الحُمَة السم",
          "source_refs": "ayn:file=0170KhalilFarahidi.Cayn.JK000930-ara1:section=heading%3A1863:headword=%D8%AD%D9%85%D9%89:root=%D8%AD%20%D9%85%20%D9%8A:sha=9283a75f6d7f3a06;mufradat:file=0502RaghibIsbahani.Mufradat.Shamela0023636-ara1:section=heading%3A363:headword=%D8%AD%D9%85%D9%89:root=%D8%AD%20%D9%85%20%D9%8A:sha=2df5f9e72e438838",
          "status": "accepted",
          "contaminated": "no",
          "shared_consensus_core": [
            "clay",
            "mud",
            "sediment"
          ]
        },
        {
          "root_id": "root_000963",
          "branch_id": "B001",
          "root_norm": "ط ي ن",
          "branch_image_ar": "مادة الطين المختلط",
          "what_is_ar": "يدخل فيه الطين المعروف والطينة وكون الأرض أو اليوم ذا طين وما كان من مادة التراب والماء المختلط.",
          "what_is_not_ar": "لا يدخل فيه وصف الطيان للثور من الطوى والجوع ولا اسم البلد فلسطين.",
          "source_refs": "0395IbnFarisQazwini.MucjamMaqayis.JK008008-ara1:heading:2233;ayn:file=0170KhalilFarahidi.Cayn.JK000930-ara1:section=heading%3A5306:headword=%D8%B7%D9%8A%D9%86:root=%D8%B7%20%D9%8A%20%D9%86:sha=7573b28ad862ca70;sihah:file=0393IbnHammadJawhari.SihahTajLugha.Shamela0023235-ara1:section=heading%3A4974:headword=%D8%B7%D9%8A%D9%86:root=%D8%B7%20%D9%8A%20%D9%86:sha=5a3f9ca810ef1c4f;tahdhib:file=tahdhib.sqlite_original:section=parent_entry_id%3D704%3Bsegment_index%3D2:headword=%D8%B7%D9%8A%D9%86:root=%D8%B7%20%D9%8A%20%D9%86:sha=6341cacea918370a;mufradat:file=0502RaghibIsbahani.Mufradat.Shamela0023636-ara1:section=heading%3A949:headword=%D8%B7%D9%8A%D9%86:root=%D8%B7%20%D9%8A%20%D9%86:sha=8fc1654547b9f973",
          "status": "accepted",
          "contaminated": "no",
          "shared_consensus_core": [
            "clay",
            "mud",
            "water"
          ]
        },
        {
          "root_id": "root_000373",
          "branch_id": "B013",
          "root_norm": "ح و ل",
          "branch_image_ar": "الحال من تراب أو طين",
          "what_is_ar": "الحال بمعنى التراب اللين أو الطين الأسود كما صرحت المصادر",
          "what_is_not_ar": "ليس هو حال الإنسان ولا الحول السنة",
          "source_refs": "ayn:file=0170KhalilFarahidi.Cayn.JK000930-ara1:section=heading%3A1837:headword=%D8%AD%D9%88%D9%84:root=%D8%AD%20%D9%88%20%D9%84:sha=087b738c7dccff99;sihah:file=0393IbnHammadJawhari.SihahTajLugha.Shamela0023235-ara1:section=heading%3A3969:headword=%D8%AD%D9%88%D9%84:root=%D8%AD%20%D9%88%20%D9%84:sha=589525ca7f2b5439",
          "status": "accepted",
          "contaminated": "no",
          "shared_consensus_core": [
            "clay",
            "mud"
          ]
        },
        {
          "root_id": "root_000541",
          "branch_id": "B004",
          "root_norm": "ر ج ج",
          "branch_image_ar": "رجرجة الماء الباقي الكدر",
          "what_is_ar": "يدخل فيه الرجرجة: بقية الماء في الحوض، أو الماء القليل في مقره، إذا اختلط بالطين واضطرب وتكدر.",
          "what_is_not_ar": "ليس الكتيبة الرجراجة ولا المرأة الرجراجة، ولا رج الشيء نفسه إلا من جهة الاضطراب الذي يفسر كدر الماء.",
          "source_refs": "0395IbnFarisQazwini.MucjamMaqayis.JK008008-ara1:heading:1257;ayn:file=0170KhalilFarahidi.Cayn.JK000930-ara1:section=heading%3A3980:headword=%D8%B1%D8%AC:root=%D8%B1%20%D8%AC:sha=ad0b4e89862b2f3b;sihah:file=0393IbnHammadJawhari.SihahTajLugha.Shamela0023235-ara1:section=heading%3A796:headword=%D8%B1%D8%AC%D8%AC:root=%D8%B1%20%D8%AC%20%D8%AC:sha=de8ca22070db5302;tahdhib:file=tahdhib.sqlite_original:section=parent_entry_id%3D541%3Bsegment_index%3D3:headword=%D8%B1%D8%AC:root=%D8%B1%20%D8%AC:sha=910a96beaa0dede2;mufradat:file=0502RaghibIsbahani.Mufradat.Shamela0023636-ara1:section=heading%3A540:headword=%D8%B1%D8%AC:root=%D8%B1%20%D8%AC:sha=cfc9e3c4a7d7ad66",
          "status": "accepted",
          "contaminated": "no",
          "shared_consensus_core": [
            "sediment",
            "water"
          ]
        },
        {
          "root_id": "root_000621",
          "branch_id": "B008",
          "root_norm": "ز ب ر",
          "branch_image_ar": "الزبير حمأة وكدر",
          "what_is_ar": "يدخل فيه الزبير بمعنى الحمأة أو الكدر.",
          "what_is_not_ar": "ليس الزبير الداهية، ولا اسم زبير، ولا زبر الكتاب.",
          "source_refs": "jamhara:file=0321IbnDuraydAzdi.JamharatLugha.JK007100-ara1:section=heading%3A719%3Asubentry%3A2%3A%D8%B2%D8%A8%D8%B1:headword=%D8%B2%D8%A8%D8%B1:root=%D8%B2%20%D8%A8%20%D8%B1:sha=cf3bbfb36a2029e7;tahdhib:file=tahdhib.sqlite_original:section=parent_entry_id%3D673%3Bsegment_index%3D23:headword=%D8%B2%D8%A8%D8%B1:root=%D8%B2%20%D8%A8%20%D8%B1:sha=5e55e17273cf182f",
          "status": "accepted",
          "contaminated": "no",
          "shared_consensus_core": [
            "sediment",
            "sludge"
          ]
        },
        {
          "root_id": "root_000760",
          "branch_id": "B004",
          "root_norm": "س و ع",
          "branch_image_ar": "الطين بالتبن",
          "what_is_ar": "السياع طين فيه تبن",
          "what_is_not_ar": "الساعة؛ إهمال الإبل؛ المذي؛ اسم الصنم",
          "source_refs": "0395IbnFarisQazwini.MucjamMaqayis.JK008008-ara1:heading:1706",
          "status": "accepted",
          "contaminated": "no",
          "shared_consensus_core": [
            "clay",
            "mud"
          ]
        },
        {
          "root_id": "root_000783",
          "branch_id": "B013",
          "root_norm": "ش ر ب",
          "branch_image_ar": "تطييب القربة وتشريبها",
          "what_is_ar": "يدخل فيه شربت القربة إذا جعل فيها طين وماء ليطيب طعمها وتشريب القربة بالماء لتنسد خروزها",
          "what_is_not_ar": "لا يدخل فيه شرب الماء من القربة",
          "source_refs": "sihah:file=0393IbnHammadJawhari.SihahTajLugha.Shamela0023235-ara1:section=heading%3A326:headword=%D8%B4%D8%B1%D8%A8:root=%D8%B4%20%D8%B1%20%D8%A8:sha=a47749be7a7fd49a;tahdhib:file=tahdhib.sqlite_original:section=parent_entry_id%3D587%3Bsegment_index%3D100:headword=%D8%B4%D8%B1%D8%A8:root=%D8%B4%20%D8%B1%20%D8%A8:sha=842661cdd7290a9b",
          "status": "accepted",
          "contaminated": "no",
          "shared_consensus_core": [
            "clay",
            "water"
          ]
        }
      ]
    }
  }
}
